roboman/__init__.py
roboman/applications/__init__.py
roboman/applications/lidar_post_detect/__init__.py
roboman/applications/lidar_post_detect/convert2tflite.py
roboman/applications/lidar_post_detect/main.py
roboman/applications/lidar_post_detect/params.py
roboman/applications/lidar_post_detect/test.py
roboman/applications/lidar_segmentation/__init__.py
roboman/applications/lidar_segmentation/main.py
roboman/applications/lidar_segmentation/viz_pred.py
roboman/applications/mono_depth/__init__.py
roboman/applications/mono_depth/main.py
roboman/applications/person_segmentation/__init__.py
roboman/applications/person_segmentation/main.py
roboman/applications/pointcloud_classification/__init__.py
roboman/applications/pointcloud_classification/main.py
roboman/applications/scene_segmentation/__init__.py
roboman/applications/scene_segmentation/main.py
roboman/custom_losses/__init__.py
roboman/custom_losses/pytorch/__init__.py
roboman/custom_losses/pytorch/depth.py
roboman/custom_losses/pytorch/pointnetloss.py
roboman/custom_losses/pytorch/segment.py
roboman/custom_losses/tensorflow/__init__.py
roboman/custom_losses/tensorflow/feature_detect.py
roboman/datacreators/__init__.py
roboman/datacreators/ai2thor/__init__.py
roboman/datacreators/ai2thor/create_dataset.py
roboman/datacreators/ai2thor/register_pcds.py
roboman/datacreators/lidar_contours/__init__.py
roboman/datacreators/lidar_contours/human_contours.py
roboman/datacreators/utils/__init__.py
roboman/datacreators/utils/cv_annotator.py
roboman/dataloaders/__init__.py
roboman/dataloaders/ade20k.py
roboman/dataloaders/cihp.py
roboman/dataloaders/coco.py
roboman/dataloaders/diode.py
roboman/dataloaders/imgcsvloader.py
roboman/dataloaders/modelnet.py
roboman/dataloaders/nyuv2.py
roboman/dataloaders/shapenet.py
roboman/dataloaders/lidar_datasets/__init__.py
roboman/dataloaders/lidar_datasets/loader.py
roboman/dataloaders/lidar_datasets/nuscenes.py
roboman/dataloaders/utils/__init__.py
roboman-0.0.1.dist-info/METADATA
roboman-0.0.1.dist-info/WHEEL
roboman-0.0.1.dist-info/top_level.txt
roboman-0.0.1.dist-info/RECORD
