Metadata-Version: 2.1
Name: roboman
Version: 0.0.1
Summary: ROBOtic perception using Modules And Neural networks- A modular perception library for machine learning in robotics use cases
Home-page: https://github.com/Homagn/roboman
Author: Homagni Saha
Author-email: Homagni Saha <homagnisaha@gmail.com>
Project-URL: Homepage, https://github.com/Homagn/roboman
Classifier: Programming Language :: Python :: 3
Classifier: License :: OSI Approved :: MIT License
Classifier: Operating System :: OS Independent
Requires-Python: >=3.7
